hexdragon/__init__.py
hexdragon/__main__.py
hexdragon-0.0.7.dist-info/LICENSE
hexdragon-0.0.7.dist-info/METADATA
hexdragon-0.0.7.dist-info/WHEEL
hexdragon-0.0.7.dist-info/entry_points.txt
hexdragon-0.0.7.dist-info/top_level.txt
hexdragon-0.0.7.dist-info/RECORD
