Metadata-Version: 2.1
Name: hexdragon
Version: 0.0.7
Summary: Print a file as coloured hexadecimal to console
Home-page: https://github.com/0xflotus/hexdragon
Author: 0xflotus
Author-email: 0xflotus+pypi@gmail.com
License: MIT
Platform: UNKNOWN
Classifier: License :: OSI Approved :: MIT License
Classifier: Programming Language :: Python :: 3
Classifier: Programming Language :: Python :: 3.9
License-File: LICENSE
Requires-Dist: argparse
